{
  "area": [
    {
      "id": "253",
      "name": "上海"
    },
    {
      "id": "254",
      "name": "安徽马鞍山"
    },
    {
      "id": "255",
      "name": "河北邯郸"
    },
    {
      "id": "256",
      "name": "河北唐山"
    },
    {
      "id": "257",
      "name": "湖北黄石"
    },
    {
      "id": "258",
      "name": "江苏常熟"
    },
    {
      "id": "259",
      "name": "江苏江阴"
    },
    {
      "id": "260",
      "name": "山东博兴"
    },
    {
      "id": "261",
      "name": "四川成都"
    },
    {
      "id": "262",
      "name": "天津"
    }
  ],
  "cangku": [
    {
      "id": "42",
      "name": "上海释辰库"
    },
    {
      "id": "43",
      "name": "常熟钢材市场库"
    },
    {
      "id": "222",
      "name": "成都达海库"
    },
    {
      "id": "223",
      "name": "成都攀钢库"
    },
    {
      "id": "224",
      "name": "成都世飞库"
    },
    {
      "id": "225",
      "name": "邯郸众朋西环库"
    },
    {
      "id": "226",
      "name": "黄石西马库"
    },
    {
      "id": "227",
      "name": "江阴联合库"
    },
    {
      "id": "228",
      "name": "马鞍山长运物流库"
    },
    {
      "id": "229",
      "name": "首瀚鑫仓库"
    },
    {
      "id": "230",
      "name": "天津克斯马库"
    },
    {
      "id": "231",
      "name": "上海新通豪仓库"
    },
    {
      "id": "232",
      "name": "释辰2号库"
    },
    {
      "id": "233",
      "name": "博兴彩涂库"
    },
    {
      "id": "3902",
      "name": "佛山宝力库"
    },
    {
      "id": "3903",
      "name": "东石良兴码头库"
    },
    {
      "id": "3904",
      "name": "万事达邯郸309库"
    }
  ],
  "gn": [
    {
      "id": "3",
      "name": "彩涂"
    },
    {
      "id": "4",
      "name": "镀锌"
    },
    {
      "id": "5",
      "name": "镀铝锌"
    },
    {
      "id": "6415",
      "name": "铝镁锰"
    },
    {
      "id": "5870",
      "name": "冷轧"
    },
    {
      "id": "5934",
      "name": "热轧"
    },
    {
      "id": "6040",
      "name": "压型板"
    },
    {
      "id": "6171",
      "name": "不锈钢"
    },
    {
      "id": "6307",
      "name": "覆膜板"
    }
  ],
  "types": [
    {
      "name": "自提",
      "value": "0"
    },
    {
      "name": "代运",
      "value": "1"
    }
  ],
  "status": [
    {
      "name": "运费核算中",
      "value": "1"
    },
    {
      "name": "待付款",
      "value": "2"
    },
    {
      "name": "待提货",
      "value": "3"
    },
    {
      "name": "开票中",
      "value": "8"
    },
    {
      "name": "待开发票",
      "value": "5"
    },
    {
      "name": "完成",
      "value": "6"
    },
    {
      "name": "取消",
      "value": "7"
    }
  ]
}